LICENSE.txt
MANIFEST.in
README.md
setup.cfg
setup.py
src/vpnchooser/__init__.py
src/vpnchooser/applicaton.py
src/vpnchooser/celery.py
src/vpnchooser/manage.py
src/vpnchooser/syncer.py
src/vpnchooser/template.cfg
src/vpnchooser.egg-info/PKG-INFO
src/vpnchooser.egg-info/SOURCES.txt
src/vpnchooser.egg-info/dependency_links.txt
src/vpnchooser.egg-info/entry_points.txt
src/vpnchooser.egg-info/namespace_packages.txt
src/vpnchooser.egg-info/not-zip-safe
src/vpnchooser.egg-info/requires.txt
src/vpnchooser.egg-info/top_level.txt
src/vpnchooser/cli/__init__.py
src/vpnchooser/cli/configuration_generator.py
src/vpnchooser/connection/__init__.py
src/vpnchooser/connection/client.py
src/vpnchooser/db/__init__.py
src/vpnchooser/db/database.py
src/vpnchooser/db/device.py
src/vpnchooser/db/user.py
src/vpnchooser/db/vpn.py
src/vpnchooser/helpers/__init__.py
src/vpnchooser/helpers/auth.py
src/vpnchooser/helpers/decorators.py
src/vpnchooser/helpers/parser.py
src/vpnchooser/helpers/fields/__init__.py
src/vpnchooser/helpers/fields/absolute_url.py
src/vpnchooser/objects/__init__.py
src/vpnchooser/objects/rule.py
src/vpnchooser/query/__init__.py
src/vpnchooser/query/rules_query.py
src/vpnchooser/resources/__init__.py
src/vpnchooser/resources/device.py
src/vpnchooser/resources/user.py
src/vpnchooser/resources/vpn.py
src/vpnchooser/static/index.html
src/vpnchooser/static/dist/app.js
src/vpnchooser/static/dist/lib.js
src/vpnchooser/static/dist/css/app.css
src/vpnchooser/static/dist/fonts/basic.icons.eot
src/vpnchooser/static/dist/fonts/basic.icons.svg
src/vpnchooser/static/dist/fonts/basic.icons.ttf
src/vpnchooser/static/dist/fonts/basic.icons.woff
src/vpnchooser/static/dist/fonts/icons.eot
src/vpnchooser/static/dist/fonts/icons.otf
src/vpnchooser/static/dist/fonts/icons.svg
src/vpnchooser/static/dist/fonts/icons.ttf
src/vpnchooser/static/dist/fonts/icons.woff
src/vpnchooser/static/dist/images/loader-large-inverted.gif
src/vpnchooser/static/dist/images/loader-large.gif
src/vpnchooser/static/dist/images/loader-medium-inverted.gif
src/vpnchooser/static/dist/images/loader-medium.gif
src/vpnchooser/static/dist/images/loader-mini-inverted.gif
src/vpnchooser/static/dist/images/loader-mini.gif
src/vpnchooser/static/dist/images/loader-small-inverted.gif
src/vpnchooser/static/dist/images/loader-small.gif
