Metadata-Version: 1.1
Name: vpnchooser
Version: 0.6.5
Summary: Web UI to switch clients between different ip rule tables
Home-page: https://github.com/cbrand/vpnchooser
Author: Christoph Brand
Author-email: christoph@brand.rest
License: UNKNOWN
Download-URL: https://github.com/cbrand/vpnchooser/tarball/0.6.5
Keywords: vpn,network,ip
Platform: UNKNOWN
Classifier: Programming Language :: Python
Classifier: Development Status :: 3 - Alpha
Classifier: Programming Language :: Python :: 3 :: Only
Classifier: Programming Language :: Python :: 3.4
Classifier: Framework :: Flask
Classifier: Topic :: System :: Networking
